mkdocs_publish_control/__init__.py
mkdocs_publish_control/plugin.py
mkdocs_publish_control-0.1.2.dist-info/LICENSE
mkdocs_publish_control-0.1.2.dist-info/METADATA
mkdocs_publish_control-0.1.2.dist-info/WHEEL
mkdocs_publish_control-0.1.2.dist-info/entry_points.txt
mkdocs_publish_control-0.1.2.dist-info/RECORD
