Metadata-Version: 2.3
Name: mkdocs-publish-control
Version: 0.1.2
Summary: MkDocs plugin to control page publishing based on metadata
License: MIT
Keywords: mkdocs,plugin,publishing,metadata,control
Author: Gabriel Dornas
Author-email: gabrielbdornas@gmail.com
Requires-Python: >=3.10,<4.0
Classifier: Development Status :: 4 - Beta
Classifier: Programming Language :: Python :: 3
Classifier: Programming Language :: Python :: 3.10
Classifier: License :: OSI Approved :: MIT License
Classifier: Operating System :: OS Independent
Classifier: Topic :: Documentation
Classifier: Topic :: Software Development :: Documentation
Requires-Dist: mkdocs (>=1.6.1,<2.0.0)
Project-URL: Documentation, https://github.com/gabrielbdornas/mkdocs-publish-control#readme
Project-URL: Homepage, https://github.com/gabrielbdornas/mkdocs-publish-control
Project-URL: Issues, https://github.com/gabrielbdornas/mkdocs-publish-control/issues
Project-URL: Repository, https://github.com/gabrielbdornas/mkdocs-publish-control
